LICENSE
MANIFEST.in
README.md
TODO.md
palu.py
setup.py
palu.egg-info/PKG-INFO
palu.egg-info/SOURCES.txt
palu.egg-info/dependency_links.txt
palu.egg-info/entry_points.txt
palu.egg-info/requires.txt
palu.egg-info/top_level.txt
test/test.html
test/test.py
test/test_input.txt