Metadata-Version: 1.0
Name: palu
Version: 0.1
Summary: Palu is a small spider, a forked of patu.
Home-page: http://github.com/marimore/palu
Author: Alex Kritikos
Author-email: alex@8bitb.us
License: UNKNOWN
Platform: UNKNOWN
